src/decoder.v
module decoder(
	input [1:0] dec_in,
	output reg [3:0] dec_out
);

always @(*) begin 
	case(dec_in)
		2'b00: dec_out<= 4'b0001;
		2'b01: dec_out<= 4'b0010;
		2'b10: dec_out<= 4'b0100;
		2'b11: dec_out<= 4'b1000;
		default: dec_out<= 4'b0000;
	endcase
end

endmodule

src/encoder.v
module encoder(
	input [3:0] enc_in,
	output reg [1:0] enc_out
);
always @(*) begin
	case(enc_in)
		4'b0000: enc_out<= 2'bxx;
		4'b0001: enc_out<= 2'b00;
		4'b0010: enc_out<= 2'b01;
		4'b0100: enc_out<= 2'b10;
		4'b1000: enc_out<= 2'b11;
		default: enc_out<= 2'bxx;
	endcase
end
endmodule

src/mux_2_1.v
module mux_2_1(
	input sel, I0, I1,
	output mux_out
);
assign mux_out= sel? I1 :I0;
endmodule

src/combo.v
module combo( 
	input wire [1:0] choice,dec_in,
	input wire sel, I0, I1,
	input wire [3:0] enc_in,
	output reg mux_out,
	output reg [1:0] enc_out,
	output reg [3:0] dec_out
);
wire mux;
wire [1:0] enc;
wire [3:0] dec;

mux_2_1 MUX(
	.sel(sel),
     	.I0(I0),
        .I1(I1),
        .mux_out(mux)
);

encoder ENC(
	.enc_in(enc_in),
        .enc_out(enc)
);

 decoder DEC(
	 .dec_in(dec_in),
	 .dec_out(dec)
);

always @(*) begin 
	mux_out=0;
	enc_out=0;
	dec_out=0;

	case(choice)
		2'b00: mux_out=mux;
		2'b01: enc_out= enc;
		2'b10: dec_out= dec;
	endcase
end
endmodule

tb/combo_tb.v
module combo_tb;

reg [1:0] choice,dec_in;
reg sel, I0, I1;
reg [3:0] enc_in;
wire mux_out;
wire [1:0] enc_out;
wire [3:0] dec_out;

combo uut(
	.choice(choice),
       	.dec_in(dec_in),
	.sel(sel),
       	.I0(I0),
       	.I1(I1),
	.enc_in(enc_in),
	.mux_out(mux_out),
	.enc_out(enc_out),
	.dec_out(dec_out)
);	

integer i;
initial begin
	choice=2'b00;
	$monitor("time=%0t \t choice=%b \t sel=%b \t I0=%b \t I1=%b \t mux_out=%b",$time, choice, sel, I0, I1,mux_out);
        for (i=0; i<8; i++) begin
		{sel,I0,I1}= i;
		#10;
	end

        $monitor("time=%0t \t choice=%b \t enc_in=%b \t enc_out=%b",$time, choice, enc_in, enc_out); 

	choice= 2'b01;
	enc_in= 4'b0001; #10;
	enc_in= 4'b0010; #10;
	enc_in= 4'b0100; #10;
	enc_in= 4'b1000; #10;
	enc_in= 4'b0000; #10;

       $monitor("time=%0t \t choice=%b \t dec_in=%b \t dec_out=%b",$time, choice, dec_in, dec_out);

       choice= 2'b10; 
       dec_in= 2'b00; #10;
       dec_in= 2'b10; #10;
       dec_in= 2'b10; #10;
       dec_in= 2'b11; #10;
       
       $finish;
end

initial begin
	$dumpfile("combo.vcd");
	$dumpvars();
end
endmodule

waveform/combo.vcd
$date
	Wed Jul 30 13:01:23 2025
$end
$version
	Icarus Verilog
$end
$timescale
	1s
$end
$scope module combo_tb $end
$var wire 1 ! mux_out $end
$var wire 2 " enc_out [1:0] $end
$var wire 4 # dec_out [3:0] $end
$var reg 1 $ I0 $end
$var reg 1 % I1 $end
$var reg 2 & choice [1:0] $end
$var reg 2 ' dec_in [1:0] $end
$var reg 4 ( enc_in [3:0] $end
$var reg 1 ) sel $end
$var integer 32 * i [31:0] $end
$scope module uut $end
$var wire 1 $ I0 $end
$var wire 1 % I1 $end
$var wire 2 + choice [1:0] $end
$var wire 2 , dec_in [1:0] $end
$var wire 4 - enc_in [3:0] $end
$var wire 1 ) sel $end
$var wire 1 . mux $end
$var wire 2 / enc [1:0] $end
$var wire 4 0 dec [3:0] $end
$var reg 4 1 dec_out [3:0] $end
$var reg 2 2 enc_out [1:0] $end
$var reg 1 ! mux_out $end
$scope module DEC $end
$var wire 2 3 dec_in [1:0] $end
$var reg 4 4 dec_out [3:0] $end
$upscope $end
$scope module ENC $end
$var wire 4 5 enc_in [3:0] $end
$var reg 2 6 enc_out [1:0] $end
$upscope $end
$scope module MUX $end
$var wire 1 $ I0 $end
$var wire 1 % I1 $end
$var wire 1 ) sel $end
$var wire 1 . mux_out $end
$upscope $end
$upscope $end
$upscope $end
$enddefinitions $end
#0
$dumpvars
bx 6
bx 5
bx 4
bx 3
b0 2
b0 1
bx 0
bx /
0.
bx -
bx ,
b0 +
b0 *
0)
bx (
bx '
b0 &
0%
0$
b0 #
b0 "
0!
$end
#10
1%
b1 *
#20
1!
1.
1$
0%
b10 *
#30
1%
b11 *
#40
0!
0.
1)
0$
0%
b100 *
#50
1!
1.
1%
b101 *
#60
0!
0.
1$
0%
b110 *
#70
1!
1.
1%
b111 *
#80
b0 /
b0 6
b0 "
b0 2
0!
b1 (
b1 -
b1 5
b1 &
b1 +
b1000 *
#90
b1 "
b1 2
b1 /
b1 6
b10 (
b10 -
b10 5
#100
b10 "
b10 2
b10 /
b10 6
b100 (
b100 -
b100 5
#110
b11 "
b11 2
b11 /
b11 6
b1000 (
b1000 -
b1000 5
#120
bx "
bx 2
bx /
bx 6
b0 (
b0 -
b0 5
#130
b1 0
b1 4
b1 #
b1 1
b0 "
b0 2
b0 '
b0 ,
b0 3
b10 &
b10 +
#140
b100 #
b100 1
b100 0
b100 4
b10 '
b10 ,
b10 3
#160
b1000 #
b1000 1
b1000 0
b1000 4
b11 '
b11 ,
b11 3
